{"version": 0.6, "generator": "Overpass API 0.7.56.9 76e5016d", "osm3s": {"timestamp_osm_base": "2021-09-21T11:44:26Z", "copyright": "The data included in this document is from www.openstreetmap.org. The data is made available under ODbL."}, "elements": [{"type": "node", "id": 276265415, "lat": 55.4561312, "lon": 13.933136, "tags": {"name": "K\u00f6pingebro", "public_transport": "stop_position", "railway": "station", "ref": "K\u00f6p", "train": "yes", "wheelchair": "yes"}}, {"type": "node", "id": 276265508, "lat": 55.5463805, "lon": 13.9493524, "tags": {"name": "Tomelilla", "public_transport": "stop_position", "railway": "station", "ref": "Tli", "train": "yes"}}, {"type": "node", "id": 276266976, "lat": 55.5410903, "lon": 14.042177, "tags": {"name": "Lunnarp", "public_transport": "stop_position", "railway": "station", "ref": "Lup", "train": "yes"}}, {"type": "node", "id": 7156929269, "lat": 55.4273931, "lon": 13.8251994, "tags": {"name": "Ystad", "public_transport": "station", "railway": "station", "railway:track_ref": "3", "ref": "Y", "train": "yes"}}]}